m1n1/__init__.py
m1n1/adt.py
m1n1/agx/__init__.py
m1n1/agx/channels.py
m1n1/agx/context.py
m1n1/agx/event.py
m1n1/agx/initdata.py
m1n1/agx/object.py
m1n1/agx/render.py
m1n1/agx/shim.py
m1n1/agx/uapi.py
m1n1/asm.py
m1n1/constructutils.py
m1n1/data/apple_regs.json
m1n1/data/arm_regs.json
m1n1/find_regs.py
m1n1/fw/__init__.py
m1n1/fw/afk/__init__.py
m1n1/fw/afk/epic.py
m1n1/fw/afk/rbep.py
m1n1/fw/agx/__init__.py
m1n1/fw/agx/channels.py
m1n1/fw/agx/cmdqueue.py
m1n1/fw/agx/handoff.py
m1n1/fw/agx/initdata.py
m1n1/fw/agx/microsequence.py
m1n1/fw/ane.py
m1n1/fw/aop/__init__.py
m1n1/fw/aop/aopep.py
m1n1/fw/aop/base.py
m1n1/fw/aop/client.py
m1n1/fw/aop/ipc.py
m1n1/fw/asc/__init__.py
m1n1/fw/asc/base.py
m1n1/fw/asc/crash.py
m1n1/fw/asc/ioreporting.py
m1n1/fw/asc/kdebug.py
m1n1/fw/asc/mgmt.py
m1n1/fw/asc/oslog.py
m1n1/fw/asc/syslog.py
m1n1/fw/avd/__init__.py
m1n1/fw/avd/decoder.py
m1n1/fw/common.py
m1n1/fw/dcp/__init__.py
m1n1/fw/dcp/client.py
m1n1/fw/dcp/dcpav.py
m1n1/fw/dcp/dcpep.py
m1n1/fw/dcp/iboot.py
m1n1/fw/dcp/ipc.py
m1n1/fw/dcp/manager.py
m1n1/fw/dcp/parse_log.py
m1n1/fw/isp/__init__.py
m1n1/fw/isp/isp_base.py
m1n1/fw/isp/isp_chan.py
m1n1/fw/isp/isp_cmd.py
m1n1/fw/isp/isp_opcodes.py
m1n1/fw/isp/isp_vid.py
m1n1/fw/mtp.py
m1n1/fw/pmp.py
m1n1/fw/smc.py
m1n1/gpiola.py
m1n1/hostutils.py
m1n1/hv/__init__.py
m1n1/hv/gdbserver/__init__.py
m1n1/hv/gdbserver/features/aarch64-core.xml
m1n1/hv/gdbserver/features/aarch64-fpu.xml
m1n1/hv/gdbserver/features/target.xml
m1n1/hv/types.py
m1n1/hv/virtio.py
m1n1/hv/virtutils.py
m1n1/hw/admac.py
m1n1/hw/aes.py
m1n1/hw/agx.py
m1n1/hw/ane.py
m1n1/hw/asc.py
m1n1/hw/atc.py
m1n1/hw/codecs/__init__.py
m1n1/hw/codecs/cs42l84.py
m1n1/hw/codecs/ssm3515.py
m1n1/hw/dart.py
m1n1/hw/dart8020.py
m1n1/hw/dart8110.py
m1n1/hw/dockchannel.py
m1n1/hw/dwc3.py
m1n1/hw/i2c.py
m1n1/hw/isp.py
m1n1/hw/jpeg.py
m1n1/hw/mca.py
m1n1/hw/nco.py
m1n1/hw/pmgr.py
m1n1/hw/pmu.py
m1n1/hw/prores.py
m1n1/hw/scaler.py
m1n1/hw/sep.py
m1n1/hw/spi.py
m1n1/hw/spmi.py
m1n1/hw/uat.py
m1n1_proxyclient-0.4.0.dist-info/METADATA
m1n1_proxyclient-0.4.0.dist-info/WHEEL
m1n1_proxyclient-0.4.0.dist-info/licenses/LICENSE
m1n1_proxyclient-0.4.0.dist-info/RECORD
